sphinxcontrib/skeleton/__init__.py
sphinxcontrib/skeleton/demo_directive.py
sphinxcontrib/skeleton/demo_role.py
sphinxcontrib_skeleton-0.0.2.dist-info/METADATA
sphinxcontrib_skeleton-0.0.2.dist-info/WHEEL
sphinxcontrib_skeleton-0.0.2.dist-info/licenses/AUTHORS.rst
sphinxcontrib_skeleton-0.0.2.dist-info/licenses/LICENSE
sphinxcontrib_skeleton-0.0.2.dist-info/RECORD
