Metadata-Version: 2.1
Name: sphinxcontrib-skeleton
Version: 0.0.2
Summary: the skeleton of a sphinx extension in the sphinxcontrib community
Project-URL: Homepage, https://github.com/username/sphinxcontrib-skeleton
Author-email: Firstname Lastname <firstname.lastname@domain.io>
License: MIT
License-File: AUTHORS.rst
License-File: LICENSE
Keywords: Python,skeleton
Classifier: Development Status :: 3 - Alpha
Classifier: Intended Audience :: Developers
Classifier: License :: OSI Approved :: MIT License
Classifier: Programming Language :: Python :: 3.8
Classifier: Programming Language :: Python :: 3.9
Classifier: Programming Language :: Python :: 3.10
Classifier: Programming Language :: Python :: 3.11
Requires-Python: >=3.8
Requires-Dist: deprecated>=1.2.14
Requires-Dist: sphinx
Provides-Extra: doc
Requires-Dist: pydata-sphinx-theme; extra == 'doc'
Requires-Dist: sphinx-autoapi; extra == 'doc'
Requires-Dist: sphinx-copybutton; extra == 'doc'
Requires-Dist: sphinx-design; extra == 'doc'
Provides-Extra: test
Requires-Dist: beautifulsoup4; extra == 'test'
Requires-Dist: pytest; extra == 'test'
Requires-Dist: pytest-cov; extra == 'test'
Requires-Dist: pytest-deadfixtures; extra == 'test'
Requires-Dist: pytest-regressions; extra == 'test'
Requires-Dist: pytest-sugar; extra == 'test'
